{
    "app": {
        "title": "Тетрис-блоки",
        "loading": "Загрузка...",
        "version": "Версия 1.0"
    },
    "menu": {
        "play": "Играть",
        "tutorial": "Обучение",
        "settings": "Настройки",
        "achievements": "Достижения",
        "leaderboard": "Рейтинг"
    },
    "game": {
        "score": "Очки",
        "combo": "Комбо",
        "highScore": "Рекорд",
        "newGame": "Новая игра",
        "pause": "Пауза",
        "resume": "Продолжить",
        "quit": "Выйти"
    },
    "tutorial": {
        "title": "Обучение",
        "next": "Далее",
        "previous": "Назад",
        "skip": "Пропустить",
        "finish": "Завершить",
        "steps": {
            "1": {
                "title": "Добро пожаловать!",
                "text": "Добро пожаловать в игру 'Тетрис-блоки'! Здесь вы будете размещать фигуры на сетке 8x8 и очищать линии для набора очков."
            },
            "2": {
                "title": "Фигуры",
                "text": "У вас всегда есть 3 фигуры на выбор. Выберите фигуру и перетащите её на игровое поле."
            },
            "3": {
                "title": "Размещение фигур",
                "text": "Перетащите фигуру на игровое поле. Зеленый цвет означает, что вы можете разместить фигуру, красный - что нет."
            },
            "4": {
                "title": "Очистка линий",
                "text": "Когда вы заполняете целую строку или столбец, они очищаются, и вы получаете очки. Старайтесь очистить несколько линий одновременно!"
            },
            "5": {
                "title": "Комбо и множители",
                "text": "Последовательные очистки линий дают вам бонус комбо, увеличивая количество получаемых очков."
            },
            "6": {
                "title": "Конец игры",
                "text": "Игра заканчивается, когда больше невозможно разместить ни одну фигуру на поле. Удачи!"
            }
        }
    },
    "settings": {
        "title": "Настройки",
        "language": "Язык",
        "sound": "Звук",
        "music": "Музыка",
        "vibration": "Вибрация",
        "darkMode": "Темная тема",
        "save": "Сохранить",
        "reset": "Сбросить"
    },
    "achievements": {
        "title": "Достижения",
        "unlocked": "Разблокировано",
        "locked": "Заблокировано",
        "progress": "Прогресс"
    },
    "gameOver": {
        "title": "Игра окончена",
        "score": "Ваш счет",
        "highScore": "Рекорд",
        "newHighScore": "Новый рекорд!",
        "continue": "Продолжить",
        "watchAd": "Смотреть рекламу для бонусных фигур",
        "restart": "Начать заново",
        "share": "Поделиться результатом",
        "menu": "В меню"
    }
}
